lz4unipy/__init__.py
lz4unipy/cmd.py
lz4unipy/handler.py
lz4unipy-2.0.1.dist-info/LICENSE
lz4unipy-2.0.1.dist-info/METADATA
lz4unipy-2.0.1.dist-info/WHEEL
lz4unipy-2.0.1.dist-info/entry_points.txt
lz4unipy-2.0.1.dist-info/top_level.txt
lz4unipy-2.0.1.dist-info/RECORD
