Metadata-Version: 2.1
Name: lz4unipy
Version: 2.0.1
Summary: unity3d compatible lz4 (un)compress tool working on Python3.
Home-page: https://github.com/CrescentApricot/lz4unipy
Author: CrescentApricot
Author-email: anzu-noreply@googlegroups.com
License: MIT License
Requires-Dist: lz4 (<3.0.0)
